siliconperception/DX120P.py
siliconperception/DX120P.py.1
siliconperception/IE120R.py
siliconperception/__init__.py
siliconperception-0.0.13.dist-info/METADATA
siliconperception-0.0.13.dist-info/WHEEL
siliconperception-0.0.13.dist-info/licenses/LICENSE
siliconperception-0.0.13.dist-info/RECORD
