Metadata-Version: 2.4
Name: siliconperception
Version: 0.0.13
Summary: Single chip image encoder and pose decoder with pretrained weights from HuggingFace
Project-URL: Homepage, https://www.siliconperception.com
Project-URL: Issues, https://github.com/siliconperception/devices
Author-email: Rob Liston <rliston@siliconperception.com>
License-File: LICENSE
Classifier: License :: OSI Approved :: MIT License
Classifier: Operating System :: OS Independent
Classifier: Programming Language :: Python :: 3
Requires-Python: >=3.8
